Metadata-Version: 2.1
Name: spedpyutils
Version: 0.0.4
Summary: Biblioteca para visualização de um arquivo sped em estrutura de tabelas hierarquicas. Compatibilidade com a biblioteca python-sped
Author: Ismael Nascimento
Author-email: ismaelnjr@icloud.com.br
License: MIT License
Keywords: sped fiscal receita federal
Classifier: Programming Language :: Python :: 3
Classifier: License :: OSI Approved :: MIT License
Classifier: Operating System :: OS Independent
License-File: LICENSE
